{
    "Activities": [
      {
        "cardContainer": "cardContainer",
        "container": "card",
        "imgContainer": "cardImg",
        "textContainer": "cardText",
        "content": [
          {
            "element": "img",
            "text": "https://play-lh.googleusercontent.com/IeNJWoKYx1waOhfWF6TiuSiWBLfqLb18lmZYXSgsH1fvb8v1IYiZr5aYWe0Gxu-pVZX3"
          },
          {
            "element": "cardHeader",
            "text": "Milestone 229"
          },
          {
            "element": "cardParagraph",
            "text": "A bar/restaurant located in the ballalh lhalb laha"
          },
          {
            "element": "button",
            "text": "More Info",
            "link": "https://music.youtube.com/watch?v=8a0thYvYCNE&list=RDAMVM0hDShZrNLts"
          }
        ]
      },
      {
        "cardContainer": "cardContainer",
        "container": "card",
        "imgContainer": "cardImg",
        "textContainer": "cardText",
        "content": [
          {
            "element": "img",
            "text": "https://play-lh.googleusercontent.com/IeNJWoKYx1waOhfWF6TiuSiWBLfqLb18lmZYXSgsH1fvb8v1IYiZr5aYWe0Gxu-pVZX3"
          },
          {
            "element": "cardHeader",
            "text": "Milestone 229"
          },
          {
            "element": "cardParagraph",
            "text": "A bar/restaurant located in the ballalh lhalb laha"
          },
          {
            "element": "button",
            "text": "More Info",
            "link": "https://music.youtube.com/watch?v=8a0thYvYCNE&list=RDAMVM0hDShZrNLts"
          }
        ]
      },
      {
        "cardContainer": "cardContainer",
        "container": "card",
        "imgContainer": "cardImg",
        "textContainer": "cardText",
        "content": [
          {
            "element": "img",
            "text": "https://play-lh.googleusercontent.com/IeNJWoKYx1waOhfWF6TiuSiWBLfqLb18lmZYXSgsH1fvb8v1IYiZr5aYWe0Gxu-pVZX3"
          },
          {
            "element": "cardHeader",
            "text": "Milestone 229"
          },
          {
            "element": "cardParagraph",
            "text": "A bar/restaurant located in the ballalh lhalb laha"
          },
          {
            "element": "button",
            "text": "More Info",
            "link": "https://music.youtube.com/watch?v=8a0thYvYCNE&list=RDAMVM0hDShZrNLts"
          }
        ]
      },
      {
        "cardContainer": "cardContainer",
        "container": "card",
        "imgContainer": "cardImg",
        "textContainer": "cardText",
        "content": [
          {
            "element": "img",
            "text": "https://play-lh.googleusercontent.com/IeNJWoKYx1waOhfWF6TiuSiWBLfqLb18lmZYXSgsH1fvb8v1IYiZr5aYWe0Gxu-pVZX3"
          },
          {
            "element": "cardHeader",
            "text": "Milestone 229"
          },
          {
            "element": "cardParagraph",
            "text": "A bar/restaurant located in the ballalh lhalb laha"
          },
          {
            "element": "button",
            "text": "More Info",
            "link": "https://music.youtube.com/watch?v=8a0thYvYCNE&list=RDAMVM0hDShZrNLts"
          }
        ]
      },
      {
        "cardContainer": "cardContainer",
        "container": "card",
        "imgContainer": "cardImg",
        "textContainer": "cardText",
        "content": [
          {
            "element": "img",
            "text": "https://play-lh.googleusercontent.com/IeNJWoKYx1waOhfWF6TiuSiWBLfqLb18lmZYXSgsH1fvb8v1IYiZr5aYWe0Gxu-pVZX3"
          },
          {
            "element": "cardHeader",
            "text": "Milestone 229"
          },
          {
            "element": "cardParagraph",
            "text": "A bar/restaurant located in the ballalh lhalb laha"
          },
          {
            "element": "button",
            "text": "More Info",
            "link": "https://music.youtube.com/watch?v=8a0thYvYCNE&list=RDAMVM0hDShZrNLts"
          }
        ]
      },
      {
        "cardContainer": "cardContainer",
        "container": "card",
        "imgContainer": "cardImg",
        "textContainer": "cardText",
        "content": [
          {
            "element": "img",
            "text": "https://play-lh.googleusercontent.com/IeNJWoKYx1waOhfWF6TiuSiWBLfqLb18lmZYXSgsH1fvb8v1IYiZr5aYWe0Gxu-pVZX3"
          },
          {
            "element": "cardHeader",
            "text": "Milestone 229"
          },
          {
            "element": "cardParagraph",
            "text": "A bar/restaurant located in the ballalh lhalb laha"
          },
          {
            "element": "button",
            "text": "More Info",
            "link": "https://music.youtube.com/watch?v=8a0thYvYCNE&list=RDAMVM0hDShZrNLts"
          }
        ]
      }
    ]
  }